CHANGES.txt
README.txt
bootstrap.py
buildout.cfg
setup.cfg
setup.py
src/repoze/__init__.py
src/repoze.bfg.layouts.egg-info/PKG-INFO
src/repoze.bfg.layouts.egg-info/SOURCES.txt
src/repoze.bfg.layouts.egg-info/dependency_links.txt
src/repoze.bfg.layouts.egg-info/namespace_packages.txt
src/repoze.bfg.layouts.egg-info/not-zip-safe
src/repoze.bfg.layouts.egg-info/requires.txt
src/repoze.bfg.layouts.egg-info/top_level.txt
src/repoze/bfg/__init__.py
src/repoze/bfg/layouts/__init__.py
src/repoze/bfg/layouts/api.py
src/repoze/bfg/layouts/configure.zcml
src/repoze/bfg/layouts/interfaces.py
src/repoze/bfg/layouts/layout.py
src/repoze/bfg/layouts/layout.txt
src/repoze/bfg/layouts/meta.zcml
src/repoze/bfg/layouts/zcml.py
src/repoze/bfg/layouts/zcml.txt
src/repoze/bfg/layouts/tests/__init__.py
src/repoze/bfg/layouts/tests/test_doctests.py
src/repoze/bfg/layouts/tests/layouts/example.css
src/repoze/bfg/layouts/tests/layouts/example.html
src/repoze/bfg/layouts/tests/layouts/example.xss