Metadata-Version: 1.0
Name: repoze.bfg.layouts
Version: 0.2
Summary: Dynamic layouts for repoze.bfg
Home-page: UNKNOWN
Author: UNKNOWN
Author-email: UNKNOWN
License: ZPL 2.1
Keywords: zope3 repoze bfg
Platform: UNKNOWN
Classifier: Development Status :: 4 - Beta
Classifier: Environment :: Web Environment
Classifier: Intended Audience :: Developers
Classifier: License :: OSI Approved :: Zope Public License
Classifier: Programming Language :: Python
Classifier: Natural Language :: English
Classifier: Operating System :: OS Independent
Classifier: Topic :: Internet :: WWW/HTTP
Classifier: Framework :: Zope3
